{
    "leg_joints":
    [
    { "name":"COM",        "sister":-1,    "child":  1,    "mother2SelfVec": [0,  0,    0.341],    "jointAxis": "UZ",   "jointRotation": 0},
    { "name":"RLEG_06",    "sister": 7,    "child":  2,    "mother2SelfVec": [0, -0.0425,   0],    "jointAxis": "UZ",   "jointRotation": 0},
    { "name":"RLEG_08",    "sister":-1,    "child":  3,    "mother2SelfVec": [0,  0,        0],    "jointAxis": "UX",   "jointRotation": 0},
    { "name":"RLEG_10",    "sister":-1,    "child":  4,    "mother2SelfVec": [0,  0,        0],    "jointAxis": "UY",   "jointRotation": 0},
    { "name":"RLEG_12",    "sister":-1,    "child":  5,    "mother2SelfVec": [0,  0,  -0.1110],    "jointAxis": "UY",   "jointRotation": 0},
    { "name":"RLEG_14",    "sister":-1,    "child":  6,    "mother2SelfVec": [0,  0,  -0.0705],    "jointAxis": "UY",   "jointRotation": 0},
    { "name":"RLEG_16",    "sister":-1,    "child": -1,    "mother2SelfVec": [0,  0,        0],    "jointAxis": "UX",   "jointRotation": 0},
    { "name":"LLEG_07",    "sister":-1,    "child":  8,    "mother2SelfVec": [0,  0.0425,   0],    "jointAxis": "UZ",   "jointRotation": 0},
    { "name":"LLEG_09",    "sister":-1,    "child":  9,    "mother2SelfVec": [0,  0,        0],    "jointAxis": "UX",   "jointRotation": 0},
    { "name":"LLEG_11",    "sister":-1,    "child": 10,    "mother2SelfVec": [0,  0,        0],    "jointAxis": "UY",   "jointRotation": 0},
    { "name":"LLEG_13",    "sister":-1,    "child": 11,    "mother2SelfVec": [0,  0,   -0.111],    "jointAxis": "UY",   "jointRotation": 0},
    { "name":"LLEG_15",    "sister":-1,    "child": 12,    "mother2SelfVec": [0,  0,  -0.0705],    "jointAxis": "UY",   "jointRotation": 0},
    { "name":"LLEG_17",    "sister":-1,    "child": -1,    "mother2SelfVec": [0,  0,        0],    "jointAxis": "UX",   "jointRotation": 0}
    ]
}